PyThermLIA/PyThermLIA.py
PyThermLIA/__init__.py
PyThermLIA/setup.py
PyThermLIA-1.0.dist-info/LICENSE
PyThermLIA-1.0.dist-info/METADATA
PyThermLIA-1.0.dist-info/WHEEL
PyThermLIA-1.0.dist-info/top_level.txt
PyThermLIA-1.0.dist-info/RECORD
